MainyDB/__init__.py
MainyDB/core.py
MainyDB/key_manager.py
MainyDB/utils.py
mainydb-1.0.3.dist-info/METADATA
mainydb-1.0.3.dist-info/WHEEL
mainydb-1.0.3.dist-info/top_level.txt
mainydb-1.0.3.dist-info/RECORD
