Metadata-Version: 2.4
Name: MainyDB
Version: 1.0.3
Summary: A lightweight, embedded MongoDB-like database in a single file
Home-page: https://github.com/dddevid/MainyDB
Author: devid
Author-email: devidrru@gmail.com
Project-URL: Bug Tracker, https://github.com/dddevid/MainyDB/issues
Classifier: Programming Language :: Python :: 3
Classifier: Programming Language :: Python :: 3.10
Classifier: License :: OSI Approved :: MIT License
Classifier: Operating System :: OS Independent
Classifier: Topic :: Database
Classifier: Topic :: Software Development :: Libraries
Requires-Python: >=3.10
Requires-Dist: Pillow>=9.0.0
Dynamic: author
Dynamic: author-email
Dynamic: classifier
Dynamic: description
Dynamic: description-content-type
Dynamic: home-page
Dynamic: requires-dist
Dynamic: requires-python
Dynamic: summary
